ledgered/__init__.py
ledgered/__version__.py
ledgered/binary.py
ledgered/github.py
ledgered/serializers.py
ledgered/devices/__init__.py
ledgered/devices/devices.json
ledgered/manifest/__init__.py
ledgered/manifest/app.py
ledgered/manifest/cli.py
ledgered/manifest/constants.py
ledgered/manifest/errors.py
ledgered/manifest/manifest.py
ledgered/manifest/tests.py
ledgered/manifest/use_cases.py
ledgered/manifest/utils.py
ledgered/utils/__init__.py
ledgered-0.13.1.dist-info/licenses/LICENSE
ledgered-0.13.1.dist-info/METADATA
ledgered-0.13.1.dist-info/WHEEL
ledgered-0.13.1.dist-info/entry_points.txt
ledgered-0.13.1.dist-info/top_level.txt
ledgered-0.13.1.dist-info/RECORD
