Metadata-Version: 2.4
Name: ledgered
Version: 0.13.1
Summary: Python tools, utils, libraries, to be used with Ledger cryptodevices
Author-email: Ledger <hello@ledger.fr>
License: MIT License
Project-URL: Home, https://github.com/LedgerHQ/ledgered
Classifier: License :: OSI Approved :: MIT License
Classifier: Programming Language :: Python :: 3
Classifier: Programming Language :: Python :: 3.9
Classifier: Programming Language :: Python :: 3.10
Classifier: Programming Language :: Python :: 3.11
Classifier: Programming Language :: Python :: 3.12
Classifier: Programming Language :: Python :: 3.13
Classifier: Operating System :: POSIX :: Linux
Classifier: Operating System :: Microsoft :: Windows
Classifier: Operating System :: MacOS :: MacOS X
Classifier: Typing :: Typed
Requires-Python: >=3.9
License-File: LICENSE
Requires-Dist: pydantic
Requires-Dist: pyelftools
Requires-Dist: pygithub
Requires-Dist: tomli
Provides-Extra: dev
Requires-Dist: pytest; extra == "dev"
Requires-Dist: pytest-cov; extra == "dev"
Dynamic: license-file
